scientio/__init__.py
scientio/session.py
scientio/drivers/__init__.py
scientio/drivers/neo4j_driver.py
scientio/interfaces/__init__.py
scientio/interfaces/operations.py
scientio/ontology/__init__.py
scientio/ontology/json_node.py
scientio/ontology/node.py
scientio/ontology/ontology.py
scientio/ontology/otype.py
scientio/util/__init__.py
scientio/util/query_builder.py
scientio-0.9.0.dist-info/METADATA
scientio-0.9.0.dist-info/WHEEL
scientio-0.9.0.dist-info/top_level.txt
scientio-0.9.0.dist-info/RECORD
