Metadata-Version: 2.1
Name: scientio
Version: 0.9.0
Summary: ScientIO is a Knowledge Graph Engine to organise and query complex data.
Home-page: https://github.com/roboy/scientio
Author: Roboy
Author-email: team@roboy.org
License: UNKNOWN
Platform: UNKNOWN
Classifier: Programming Language :: Python :: 3
Classifier: Operating System :: OS Independent
Requires-Python: >=3.7
Requires-Dist: pytz
Requires-Dist: neo4j
Requires-Dist: pyyaml
Requires-Dist: reggol
